nevergonnagiveyouup/__init__.py
nevergonnagiveyouup/__main__.py
nevergonnagiveyouup-0.1.0.dist-info/METADATA
nevergonnagiveyouup-0.1.0.dist-info/WHEEL
nevergonnagiveyouup-0.1.0.dist-info/entry_points.txt
nevergonnagiveyouup-0.1.0.dist-info/licenses/LICENSE
nevergonnagiveyouup-0.1.0.dist-info/RECORD
