Metadata-Version: 2.3
Name: nevergonnagiveyouup
Version: 0.1.0
Summary: Never gonna let you down
Project-URL: homepage, https://youtu.be/dQw4w9WgXcQ?si=9DdFPcmcprsOGYA0
Author-email: Dowon <ks2515@naver.com>
License: MIT
License-File: LICENSE
Keywords: give,gonna,never,up,you
Classifier: Intended Audience :: Healthcare Industry
Classifier: Topic :: Games/Entertainment :: Fortune Cookies
Classifier: Topic :: Multimedia :: Video
Requires-Python: >=3.8
